<profile>

<ReportVersion>
<Version>2020.1</Version>
</ReportVersion>

<UserAssignments>
<unit>ns</unit>
<ProductFamily>kintex7</ProductFamily>
<Part>xc7k325t-ffg900-2</Part>
<TopModelName>check_note_update</TopModelName>
<TargetClockPeriod>10.00</TargetClockPeriod>
<ClockUncertainty>1.25</ClockUncertainty>
</UserAssignments>

<PerformanceEstimates>
<PipelineType>none</PipelineType>
<SummaryOfTimingAnalysis>
<unit>ns</unit>
<EstimatedClockPeriod>8.550</EstimatedClockPeriod>
</SummaryOfTimingAnalysis>
<SummaryOfOverallLatency>
<unit>clock cycles</unit>
<Best-caseLatency>66816</Best-caseLatency>
<Average-caseLatency>66816</Average-caseLatency>
<Worst-caseLatency>66816</Worst-caseLatency>
<Best-caseRealTimeLatency>0.668 ms</Best-caseRealTimeLatency>
<Average-caseRealTimeLatency>0.668 ms</Average-caseRealTimeLatency>
<Worst-caseRealTimeLatency>0.668 ms</Worst-caseRealTimeLatency>
<Interval-min>66816</Interval-min>
<Interval-max>66816</Interval-max>
</SummaryOfOverallLatency>
<SummaryOfLoopLatency>
<LOOP_check_note_update1>
<TripCount>256</TripCount>
<Latency>66815</Latency>
<IterationLatency>261</IterationLatency>
<LOOP_check_note_update_function>
<TripCount>256</TripCount>
<Latency>258</Latency>
<PipelineII>1</PipelineII>
<PipelineDepth>4</PipelineDepth>
</LOOP_check_note_update_function>
</LOOP_check_note_update1>
</SummaryOfLoopLatency>
</PerformanceEstimates>

<AreaEstimates>
<Resources>
<BRAM_18K>0</BRAM_18K>
<DSP48E>0</DSP48E>
<FF>244</FF>
<LUT>524</LUT>
<URAM>0</URAM>
</Resources>
<AvailableResources>
<BRAM_18K>890</BRAM_18K>
<DSP48E>840</DSP48E>
<FF>407600</FF>
<LUT>203800</LUT>
<URAM>0</URAM>
</AvailableResources>
</AreaEstimates>

<InterfaceSummary>
<RtlPorts>
<name>ap_clk</name>
<Object>check_note_update</Object>
<Type>return value</Type>
<Scope></Scope>
<IOProtocol>ap_ctrl_hs</IOProtocol>
<IOConfig></IOConfig>
<Dir>in</Dir>
<Bits>1</Bits>
<Attribute>control</Attribute>
</RtlPorts>
<RtlPorts>
<name>ap_rst</name>
<Object>check_note_update</Object>
<Type>return value</Type>
<Scope></Scope>
<IOProtocol>ap_ctrl_hs</IOProtocol>
<IOConfig></IOConfig>
<Dir>in</Dir>
<Bits>1</Bits>
<Attribute>control</Attribute>
</RtlPorts>
<RtlPorts>
<name>ap_start</name>
<Object>check_note_update</Object>
<Type>return value</Type>
<Scope></Scope>
<IOProtocol>ap_ctrl_hs</IOProtocol>
<IOConfig></IOConfig>
<Dir>in</Dir>
<Bits>1</Bits>
<Attribute>control</Attribute>
</RtlPorts>
<RtlPorts>
<name>ap_done</name>
<Object>check_note_update</Object>
<Type>return value</Type>
<Scope></Scope>
<IOProtocol>ap_ctrl_hs</IOProtocol>
<IOConfig></IOConfig>
<Dir>out</Dir>
<Bits>1</Bits>
<Attribute>control</Attribute>
</RtlPorts>
<RtlPorts>
<name>ap_idle</name>
<Object>check_note_update</Object>
<Type>return value</Type>
<Scope></Scope>
<IOProtocol>ap_ctrl_hs</IOProtocol>
<IOConfig></IOConfig>
<Dir>out</Dir>
<Bits>1</Bits>
<Attribute>control</Attribute>
</RtlPorts>
<RtlPorts>
<name>ap_ready</name>
<Object>check_note_update</Object>
<Type>return value</Type>
<Scope></Scope>
<IOProtocol>ap_ctrl_hs</IOProtocol>
<IOConfig></IOConfig>
<Dir>out</Dir>
<Bits>1</Bits>
<Attribute>control</Attribute>
</RtlPorts>
<RtlPorts>
<name>j</name>
<Object>j</Object>
<Type>scalar</Type>
<Scope></Scope>
<IOProtocol>ap_none</IOProtocol>
<IOConfig></IOConfig>
<Dir>in</Dir>
<Bits>8</Bits>
<Attribute>data</Attribute>
</RtlPorts>
<RtlPorts>
<name>H_address0</name>
<Object>H</Object>
<Type>array</Type>
<Scope></Scope>
<IOProtocol>ap_memory</IOProtocol>
<IOConfig></IOConfig>
<Dir>out</Dir>
<Bits>15</Bits>
<Attribute>address</Attribute>
</RtlPorts>
<RtlPorts>
<name>H_ce0</name>
<Object>H</Object>
<Type>array</Type>
<Scope></Scope>
<IOProtocol>ap_memory</IOProtocol>
<IOConfig></IOConfig>
<Dir>out</Dir>
<Bits>1</Bits>
<Attribute>control</Attribute>
</RtlPorts>
<RtlPorts>
<name>H_q0</name>
<Object>H</Object>
<Type>array</Type>
<Scope></Scope>
<IOProtocol>ap_memory</IOProtocol>
<IOConfig></IOConfig>
<Dir>in</Dir>
<Bits>1</Bits>
<Attribute>data</Attribute>
</RtlPorts>
<RtlPorts>
<name>H_address1</name>
<Object>H</Object>
<Type>array</Type>
<Scope></Scope>
<IOProtocol>ap_memory</IOProtocol>
<IOConfig></IOConfig>
<Dir>out</Dir>
<Bits>15</Bits>
<Attribute>address</Attribute>
</RtlPorts>
<RtlPorts>
<name>H_ce1</name>
<Object>H</Object>
<Type>array</Type>
<Scope></Scope>
<IOProtocol>ap_memory</IOProtocol>
<IOConfig></IOConfig>
<Dir>out</Dir>
<Bits>1</Bits>
<Attribute>control</Attribute>
</RtlPorts>
<RtlPorts>
<name>H_q1</name>
<Object>H</Object>
<Type>array</Type>
<Scope></Scope>
<IOProtocol>ap_memory</IOProtocol>
<IOConfig></IOConfig>
<Dir>in</Dir>
<Bits>1</Bits>
<Attribute>data</Attribute>
</RtlPorts>
<RtlPorts>
<name>r_V_4_address0</name>
<Object>r_V_4</Object>
<Type>array</Type>
<Scope></Scope>
<IOProtocol>ap_memory</IOProtocol>
<IOConfig></IOConfig>
<Dir>out</Dir>
<Bits>15</Bits>
<Attribute>address</Attribute>
</RtlPorts>
<RtlPorts>
<name>r_V_4_ce0</name>
<Object>r_V_4</Object>
<Type>array</Type>
<Scope></Scope>
<IOProtocol>ap_memory</IOProtocol>
<IOConfig></IOConfig>
<Dir>out</Dir>
<Bits>1</Bits>
<Attribute>control</Attribute>
</RtlPorts>
<RtlPorts>
<name>r_V_4_q0</name>
<Object>r_V_4</Object>
<Type>array</Type>
<Scope></Scope>
<IOProtocol>ap_memory</IOProtocol>
<IOConfig></IOConfig>
<Dir>in</Dir>
<Bits>5</Bits>
<Attribute>data</Attribute>
</RtlPorts>
<RtlPorts>
<name>r_V_4_address1</name>
<Object>r_V_4</Object>
<Type>array</Type>
<Scope></Scope>
<IOProtocol>ap_memory</IOProtocol>
<IOConfig></IOConfig>
<Dir>out</Dir>
<Bits>15</Bits>
<Attribute>address</Attribute>
</RtlPorts>
<RtlPorts>
<name>r_V_4_ce1</name>
<Object>r_V_4</Object>
<Type>array</Type>
<Scope></Scope>
<IOProtocol>ap_memory</IOProtocol>
<IOConfig></IOConfig>
<Dir>out</Dir>
<Bits>1</Bits>
<Attribute>control</Attribute>
</RtlPorts>
<RtlPorts>
<name>r_V_4_we1</name>
<Object>r_V_4</Object>
<Type>array</Type>
<Scope></Scope>
<IOProtocol>ap_memory</IOProtocol>
<IOConfig></IOConfig>
<Dir>out</Dir>
<Bits>1</Bits>
<Attribute>control</Attribute>
</RtlPorts>
<RtlPorts>
<name>r_V_4_d1</name>
<Object>r_V_4</Object>
<Type>array</Type>
<Scope></Scope>
<IOProtocol>ap_memory</IOProtocol>
<IOConfig></IOConfig>
<Dir>out</Dir>
<Bits>5</Bits>
<Attribute>data</Attribute>
</RtlPorts>
<RtlPorts>
<name>r_copy_V_4_address1</name>
<Object>r_copy_V_4</Object>
<Type>array</Type>
<Scope></Scope>
<IOProtocol>ap_memory</IOProtocol>
<IOConfig></IOConfig>
<Dir>out</Dir>
<Bits>8</Bits>
<Attribute>address</Attribute>
</RtlPorts>
<RtlPorts>
<name>r_copy_V_4_ce1</name>
<Object>r_copy_V_4</Object>
<Type>array</Type>
<Scope></Scope>
<IOProtocol>ap_memory</IOProtocol>
<IOConfig></IOConfig>
<Dir>out</Dir>
<Bits>1</Bits>
<Attribute>control</Attribute>
</RtlPorts>
<RtlPorts>
<name>r_copy_V_4_we1</name>
<Object>r_copy_V_4</Object>
<Type>array</Type>
<Scope></Scope>
<IOProtocol>ap_memory</IOProtocol>
<IOConfig></IOConfig>
<Dir>out</Dir>
<Bits>1</Bits>
<Attribute>control</Attribute>
</RtlPorts>
<RtlPorts>
<name>r_copy_V_4_d1</name>
<Object>r_copy_V_4</Object>
<Type>array</Type>
<Scope></Scope>
<IOProtocol>ap_memory</IOProtocol>
<IOConfig></IOConfig>
<Dir>out</Dir>
<Bits>5</Bits>
<Attribute>data</Attribute>
</RtlPorts>
<RtlPorts>
<name>q_V_address0</name>
<Object>q_V</Object>
<Type>array</Type>
<Scope>global</Scope>
<IOProtocol>ap_memory</IOProtocol>
<IOConfig></IOConfig>
<Dir>out</Dir>
<Bits>8</Bits>
<Attribute>address</Attribute>
</RtlPorts>
<RtlPorts>
<name>q_V_ce0</name>
<Object>q_V</Object>
<Type>array</Type>
<Scope>global</Scope>
<IOProtocol>ap_memory</IOProtocol>
<IOConfig></IOConfig>
<Dir>out</Dir>
<Bits>1</Bits>
<Attribute>control</Attribute>
</RtlPorts>
<RtlPorts>
<name>q_V_q0</name>
<Object>q_V</Object>
<Type>array</Type>
<Scope>global</Scope>
<IOProtocol>ap_memory</IOProtocol>
<IOConfig></IOConfig>
<Dir>in</Dir>
<Bits>5</Bits>
<Attribute>data</Attribute>
</RtlPorts>
</InterfaceSummary>

</profile>
